netdumplings/__init__.py
netdumplings/_shared.py
netdumplings/_version.py
netdumplings/dumpling.py
netdumplings/dumplingchef.py
netdumplings/dumplingeater.py
netdumplings/dumplinghub.py
netdumplings/dumplingkitchen.py
netdumplings/exceptions.py
netdumplings/console/__init__.py
netdumplings/console/_shared.py
netdumplings/console/hub.py
netdumplings/console/hubdetails.py
netdumplings/console/hubstatus.py
netdumplings/console/print.py
netdumplings/console/sniff.py
netdumplings/data/logging.json
netdumplings/dumplingchefs/__init__.py
netdumplings/dumplingchefs/arpchef.py
netdumplings/dumplingchefs/dnslookupchef.py
netdumplings/dumplingchefs/packetcountchef.py
netdumplings-0.5.1.dist-info/LICENSE
netdumplings-0.5.1.dist-info/METADATA
netdumplings-0.5.1.dist-info/WHEEL
netdumplings-0.5.1.dist-info/entry_points.txt
netdumplings-0.5.1.dist-info/top_level.txt
netdumplings-0.5.1.dist-info/RECORD
