Metadata-Version: 2.1
Name: netdumplings
Version: 0.5.1
Summary: A framework for distributed network packet sniffing and processing.
Home-page: https://github.com/mjoblin/netdumplings
Author: Mike Joblin
Author-email: mike@tastymoss.com
License: MIT
Download-URL: https://pypi.python.org/pypi/netdumplings
Platform: UNKNOWN
Classifier: Intended Audience :: Developers
Classifier: Intended Audience :: System Administrators
Classifier: License :: OSI Approved :: MIT License
Classifier: Programming Language :: Python :: 3.7
Classifier: Topic :: System :: Monitoring
Classifier: Topic :: System :: Networking
Classifier: Topic :: System :: Networking :: Monitoring
Requires-Dist: click (~=7.1)
Requires-Dist: colorama
Requires-Dist: pygments
Requires-Dist: scapy (~=2.4.3)
Requires-Dist: termcolor
Requires-Dist: websockets (~=8.1.0)
Provides-Extra: dev
Requires-Dist: flake8 ; extra == 'dev'
Requires-Dist: mypy ; extra == 'dev'
Requires-Dist: sphinx ; extra == 'dev'
Requires-Dist: sphinx-autodoc-typehints ; extra == 'dev'
Requires-Dist: asynctest ; extra == 'dev'
Requires-Dist: pytest ; extra == 'dev'
Requires-Dist: pytest-asyncio ; extra == 'dev'
Requires-Dist: pytest-cov ; extra == 'dev'
Requires-Dist: pytest-mock ; extra == 'dev'
Requires-Dist: pytest-sugar ; extra == 'dev'
